flatspark/__init__.py
flatspark/functions.py
flatspark-0.1.0.dist-info/WHEEL
flatspark-0.1.0.dist-info/METADATA
flatspark-0.1.0.dist-info/RECORD
