Metadata-Version: 2.3
Name: flatspark
Version: 0.1.0
Summary: Add your description here
Author: bombercorny
Requires-Python: >=3.13
